benboerba_mcp/__init__.py
benboerba_mcp-0.1.0.dist-info/METADATA
benboerba_mcp-0.1.0.dist-info/WHEEL
benboerba_mcp-0.1.0.dist-info/entry_points.txt
benboerba_mcp-0.1.0.dist-info/RECORD
